marsworks/__init__.py
marsworks/asyncclient.py
marsworks/helpers.py
marsworks/manifest.py
marsworks/origin/__init__.py
marsworks/origin/enums.py
marsworks/origin/exceptions.py
marsworks/origin/rest.py
marsworks/origin/serializer.py
marsworks/origin/tools.py
marsworks/partialmanifest.py
marsworks/photo.py
marsworks/syncclient.py
marsworks-0.7.0.dist-info/LICENSE
marsworks-0.7.0.dist-info/WHEEL
marsworks-0.7.0.dist-info/METADATA
marsworks-0.7.0.dist-info/RECORD
