Metadata-Version: 2.1
Name: marsworks
Version: 0.7.0
Summary: An API Wrapper around NASA's Mars Rover Photos API written in Python; providing sync and async support.
Home-page: https://github.com/mooncell07/Marsworks
License: MIT
Keywords: Mars Photos,Api-Wrapper,Async,NASA
Author: mooncell07
Author-email: mooncell07@users.noreply.github.com
Requires-Python: >=3.7,<4.0
Classifier: License :: OSI Approved :: MIT License
Classifier: Programming Language :: Python :: 3
Classifier: Programming Language :: Python :: 3.7
Classifier: Programming Language :: Python :: 3.8
Classifier: Programming Language :: Python :: 3.9
Requires-Dist: httpx (>=0.18.2,<0.19.0)
Project-URL: Documentation, https://mooncell07.github.io/Marsworks/
